{"name":"Lucky Stadium","frenchName":null,"japaneseName":null,"cards":{"-77127162":{"name":"Lucky Stadium","type":"TRAINER","rarity":"NONE","number":-42,"wikiLink":"Lucky_Stadium_(Neo_Destiny_100)","picture":"LuckyStadiumPromoChugokuShikoku.jpg","pokemonNumber":-42,"count":1,"explanation":"World Challenge Summer (Chūgoku/Shikoku conference)","frenchName":null,"japaneseName":null,"id":-77127162},"1174711650":{"name":"Lucky Stadium","type":"TRAINER","rarity":"NONE","number":-42,"wikiLink":"Lucky_Stadium_(Neo_Destiny_100)","picture":"LuckyStadiumPromoKansai.jpg","pokemonNumber":-42,"count":1,"explanation":"World Challenge Summer (Kansai conference)","frenchName":null,"japaneseName":null,"id":1174711650},"-1084146921":{"name":"Lucky Stadium","type":"TRAINER","rarity":"NONE","number":-42,"wikiLink":"Lucky_Stadium_(Neo_Destiny_100)","picture":"LuckyStadiumPromoHokkaido.jpg","pokemonNumber":-42,"count":1,"explanation":"World Challenge Summer (Hokkaidō conference)","frenchName":null,"japaneseName":null,"id":-1084146921},"-608986263":{"name":"Lucky Stadium","type":"TRAINER","rarity":"NONE","number":-42,"wikiLink":"Lucky_Stadium_(Neo_Destiny_100)","picture":"LuckyStadiumPromoTohoku.jpg","pokemonNumber":-42,"count":1,"explanation":"World Challenge Summer (Tōhoku conference)","frenchName":null,"japaneseName":null,"id":-608986263},"337095020":{"name":"Lucky Stadium","type":"TRAINER","rarity":"NONE","number":-42,"wikiLink":"Lucky_Stadium_(Neo_Destiny_100)","picture":"LuckyStadiumPromoKanto.jpg","pokemonNumber":-42,"count":1,"explanation":"World Challenge Summer (Kantō conference)","frenchName":null,"japaneseName":null,"id":337095020},"1735926452":{"name":"Lucky Stadium","type":"TRAINER","rarity":"NONE","number":-42,"wikiLink":"Lucky_Stadium_(Neo_Destiny_100)","picture":"LuckyStadiumPromoChubu.jpg","pokemonNumber":-42,"count":1,"explanation":"World Challenge Summer (Chūbu conference)","frenchName":null,"japaneseName":null,"id":1735926452},"1345770552":{"name":"Lucky Stadium","type":"TRAINER","rarity":"NONE","number":-42,"wikiLink":"Lucky_Stadium_(Neo_Destiny_100)","picture":"LuckyStadiumPromoKyushu.jpg","pokemonNumber":-42,"count":1,"explanation":"World Challenge Summer (Kyūshū conference)","frenchName":null,"japaneseName":null,"id":1345770552},"614885032":{"name":"Lucky Stadium","type":"TRAINER","rarity":"NONE","number":-42,"wikiLink":"Lucky_Stadium_(Neo_Destiny_100)","picture":"LuckyStadiumPromoHokushinetsu.jpg","pokemonNumber":-42,"count":1,"explanation":"World Challenge Summer (Hokushin'etsu conference)","frenchName":null,"japaneseName":null,"id":614885032}},"language":"JP","image":"","showNumbers":false}