{"name":"Theater Limited VS Pack","frenchName":"Pack VS cinéma","japaneseName":null,"cards":{"1405549926":{"name":"Oakley's Ariados","type":"GRASS","type2":null,"rarity":"NONE","number":1,"wikiLink":"Oakley's_Ariados_(Theater_VS_Pack_1)","picture":"OakleyAriadosTheaterVSPack1.jpg","pokemonNumber":168,"count":1,"explanation":null,"frenchName":"","japaneseName":"リオンのアリアドス","illustrator":"Kagemaru Himeno","bulbapediaId":"OakleyAriadosTheaterVSPack1.jpg","id":1405549926},"1048814914":{"name":"Ross's Wailmer","type":"WATER","type2":null,"rarity":"NONE","number":5,"wikiLink":"Ross's_Wailmer_(Theater_VS_Pack_5)","picture":"RossWailmerTheaterVSPack5.jpg","pokemonNumber":320,"count":1,"explanation":null,"frenchName":"","japaneseName":"ロッシのホエルコ","illustrator":"Atsuko Nishida","bulbapediaId":"RossWailmerTheaterVSPack5.jpg","id":1048814914},"-1051208298":{"name":"Energy Restore","type":"TRAINER","type2":null,"rarity":"NONE","number":13,"wikiLink":"Energy_Restore_(Expedition_141)","picture":"EnergyRestoreMajesticDawn81.jpg","pokemonNumber":-42,"count":1,"explanation":null,"frenchName":"","japaneseName":"エネルギー再生","illustrator":"Ryo Ueda, Hideyuki Nakajima","bulbapediaId":"EnergyRestoreMajesticDawn81.jpg","id":-1051208298},"-1472645924":{"name":"Misty's Politoed","type":"WATER","type2":null,"rarity":"NONE","number":3,"wikiLink":"Misty's_Politoed_(Theater_VS_Pack_3)","picture":"MistyPolitoedTheaterVSPack3.jpg","pokemonNumber":186,"count":1,"explanation":null,"frenchName":"Tarpaud de Ondine","japaneseName":"カスミのニョロトノ","illustrator":"Hisao Nakamura","bulbapediaId":"MistyPolitoedTheaterVSPack3.jpg","id":-1472645924},"-1653120513":{"name":"Annie's Espeon","type":"PSYCHIC","type2":null,"rarity":"NONE","number":7,"wikiLink":"Annie's_Espeon_(Theater_VS_Pack_7)","picture":"AnnieEspeonTheaterVSPack7.jpg","pokemonNumber":196,"count":1,"explanation":null,"frenchName":"","japaneseName":"ザンナーのエーフィ","illustrator":"Kagemaru Himeno","bulbapediaId":"AnnieEspeonTheaterVSPack7.jpg","id":-1653120513},"-659768220":{"name":"Alto Mare's Latios","type":"COLORLESS","type2":null,"rarity":"NONE","number":12,"wikiLink":"Alto_Mare's_Latios_(Theater_VS_Pack_12)","picture":"AltoMareLatiosTheaterVSPack12.jpg","pokemonNumber":381,"count":1,"explanation":null,"frenchName":"","japaneseName":"水の都のラティオス","illustrator":"Mitsuhiro Arita","bulbapediaId":"AltoMareLatiosTheaterVSPack12.jpg","id":-659768220},"-1086603277":{"name":"Grass Energy","type":"ENERGY","type2":null,"rarity":"NONE","number":-42,"wikiLink":"Grass_Energy_(TCG)","picture":"GrassEnergyExpedition162.jpg","pokemonNumber":-42,"count":3,"explanation":null,"frenchName":"Énergie Plante","japaneseName":"草エネルギー","illustrator":"Keiji Kinebuchi","bulbapediaId":"GrassEnergyExpedition162.jpg","id":-1086603277},"-1923335401":{"name":"Fighting Energy","type":"ENERGY","type2":null,"rarity":"NONE","number":-42,"wikiLink":"Fighting_Energy_(TCG)","picture":"FightingEnergyExpedition160.jpg","pokemonNumber":-42,"count":3,"explanation":null,"frenchName":"Énergie Combat","japaneseName":"闘エネルギー","illustrator":"Keiji Kinebuchi","bulbapediaId":"FightingEnergyExpedition160.jpg","id":-1923335401},"-1176975404":{"name":"Energy Search","type":"TRAINER","type2":null,"rarity":"NONE","number":14,"wikiLink":"Energy_Search_(Fossil_59)","picture":"EnergySearchExpedition153.jpg","pokemonNumber":-42,"count":1,"explanation":null,"frenchName":"","japaneseName":"エネルギー転送","illustrator":"Keiji Kinebuchi, Ryo Ueda, Studio Bora Inc., Kai Ishikawa","bulbapediaId":"EnergySearchExpedition153.jpg","id":-1176975404},"1094814764":{"name":"Switch","type":"TRAINER","type2":null,"rarity":"NONE","number":17,"wikiLink":"Switch_(Base_Set_95)","picture":"SwitchExpedition157.jpg","pokemonNumber":-42,"count":1,"explanation":null,"frenchName":"","japaneseName":"ポケモンいれかえ","illustrator":"Keiji Kinebuchi, 5ban Graphics, Ryo Ueda, Hiromichi Sugiyama, Ayaka Yoshida, Studio Bora Inc., Hideaki Hakozaki","bulbapediaId":"SwitchExpedition157.jpg","id":1094814764},"-1094969070":{"name":"Alto Mare's Latias","type":"COLORLESS","type2":null,"rarity":"NONE","number":11,"wikiLink":"Alto_Mare's_Latias_(Theater_VS_Pack_11)","picture":"AltoMareLatiasTheaterVSPack11.jpg","pokemonNumber":380,"count":1,"explanation":null,"frenchName":"","japaneseName":"水の都のラティアス","illustrator":"Mitsuhiro Arita","bulbapediaId":"AltoMareLatiasTheaterVSPack11.jpg","id":-1094969070},"-106732915":{"name":"Soul Dew","type":"TRAINER","type2":null,"rarity":"NONE","number":16,"wikiLink":"Soul_Dew_(Theater_VS_Pack_16)","picture":"SoulDewTheaterVSPack16.jpg","pokemonNumber":-42,"count":1,"explanation":null,"frenchName":"","japaneseName":"こころのしずく","illustrator":"Hiromichi Sugiyama","bulbapediaId":"SoulDewTheaterVSPack16.jpg","id":-106732915},"-1657842721":{"name":"Alto Mare's Kabutops","type":"FIGHTING","type2":null,"rarity":"NONE","number":8,"wikiLink":"Alto_Mare's_Kabutops_(Theater_VS_Pack_8)","picture":"AltoMareKabutopsTheaterVSPack8.jpg","pokemonNumber":141,"count":1,"explanation":null,"frenchName":"","japaneseName":"水の都のカブトプス","illustrator":"Midori Harada","bulbapediaId":"AltoMareKabutopsTheaterVSPack8.jpg","id":-1657842721},"-2006335655":{"name":"Alto Mare's Pidgeotto","type":"COLORLESS","type2":null,"rarity":"NONE","number":10,"wikiLink":"Alto_Mare's_Pidgeotto_(Theater_VS_Pack_10)","picture":"AltoMarePidgeottoTheaterVSPack10.jpg","pokemonNumber":17,"count":1,"explanation":null,"frenchName":"","japaneseName":"水の都のピジョン","illustrator":"Kouki Saitou","bulbapediaId":"AltoMarePidgeottoTheaterVSPack10.jpg","id":-2006335655},"1946196978":{"name":"Brock's Crobat","type":"GRASS","type2":null,"rarity":"NONE","number":2,"wikiLink":"Brock's_Crobat_(Theater_VS_Pack_2)","picture":"BrockCrobatTheaterVSPack2.jpg","pokemonNumber":169,"count":1,"explanation":null,"frenchName":"Nostenfer de Pierre","japaneseName":"タケシのクロバット","illustrator":"Shin-ichi Yoshikawa","bulbapediaId":"BrockCrobatTheaterVSPack2.jpg","id":1946196978},"1717094605":{"name":"Misty's Corsola","type":"WATER","type2":null,"rarity":"NONE","number":4,"wikiLink":"Misty's_Corsola_(Theater_VS_Pack_4)","picture":"MistyCorsolaTheaterVSPack4.jpg","pokemonNumber":222,"count":1,"explanation":null,"frenchName":"Corayon de Ondine","japaneseName":"カスミのサニーゴ","illustrator":"Hisao Nakamura","bulbapediaId":"MistyCorsolaTheaterVSPack4.jpg","id":1717094605},"885949912":{"name":"Alto Mare's Aerodactyl","type":"FIGHTING","type2":null,"rarity":"NONE","number":9,"wikiLink":"Alto_Mare's_Aerodactyl_(Theater_VS_Pack_9)","picture":"AltoMareAerodactylTheaterVSPack9.jpg","pokemonNumber":142,"count":1,"explanation":null,"frenchName":"","japaneseName":"水の都のプテラ","illustrator":"Midori Harada","bulbapediaId":"AltoMareAerodactylTheaterVSPack9.jpg","id":885949912},"-1508959817":{"name":"Alto Mare Cube","type":"TRAINER","type2":null,"rarity":"NONE","number":18,"wikiLink":"Alto_Mare_Cube_(Theater_VS_Pack_18)","picture":"AltoMareCubeTheaterVSPack18.jpg","pokemonNumber":-42,"count":1,"explanation":null,"frenchName":"","japaneseName":"アルトマーレキューブ","illustrator":"\"Big Mama\" Tagawa","bulbapediaId":"AltoMareCubeTheaterVSPack18.jpg","id":-1508959817},"74910702":{"name":"Potion","type":"TRAINER","type2":null,"rarity":"NONE","number":15,"wikiLink":"Potion_(Base_Set_94)","picture":"PotionExpedition156.jpg","pokemonNumber":-42,"count":1,"explanation":null,"frenchName":"","japaneseName":"きずぐすり","illustrator":"Keiji Kinebuchi, 5ban Graphics, Ryo Ueda, Ayaka Yoshida, Toyste Beach, Shin-ichi Yoshikawa","bulbapediaId":"PotionBaseSet94.jpg","id":74910702},"1128015334":{"name":"Alto Mare's Xatu","type":"PSYCHIC","type2":null,"rarity":"NONE","number":6,"wikiLink":"Alto_Mare's_Xatu_(Theater_VS_Pack_6)","picture":"AltoMareXatuTheaterVSPack6.jpg","pokemonNumber":178,"count":1,"explanation":null,"frenchName":"","japaneseName":"水の都のネイティオ","illustrator":"Kouki Saitou","bulbapediaId":"AltoMareXatuTheaterVSPack6.jpg","id":1128015334},"1624192884":{"name":"Psychic Energy","type":"ENERGY","type2":null,"rarity":"NONE","number":-42,"wikiLink":"Psychic_Energy_(TCG)","picture":"PsychicEnergyExpedition164.jpg","pokemonNumber":-42,"count":3,"explanation":null,"frenchName":"Énergie Psy","japaneseName":"超エネルギー","illustrator":"Keiji Kinebuchi","bulbapediaId":"PsychicEnergyExpedition164.jpg","id":1624192884},"2123287218":{"name":"Water Energy","type":"ENERGY","type2":null,"rarity":"NONE","number":-42,"wikiLink":"Water_Energy_(TCG)","picture":"WaterEnergyExpedition165.jpg","pokemonNumber":-42,"count":3,"explanation":null,"frenchName":"Énergie Eau","japaneseName":"水エネルギー","illustrator":"Keiji Kinebuchi","bulbapediaId":"WaterEnergyExpedition165.jpg","id":2123287218}},"language":"JP","image":"SetSymbolVS.png","showNumbers":false,"numberOfZeros":3,"numberSuffix":"018"}